Metadata-Version: 2.1
Name: eh-tabular-deepchecks
Version: 0.0.4b0
Summary: mantained deepchecks tabular module
Home-page: https://github.com/DanielAvdar/deepchecks
License: AGPL-3.0
Author: deepchecks
Requires-Python: >=3.9,<3.13
Classifier: License :: OSI Approved :: GNU Affero General Public License v3
Classifier: Programming Language :: Python :: 3
Classifier: Programming Language :: Python :: 3.9
Classifier: Programming Language :: Python :: 3.10
Classifier: Programming Language :: Python :: 3.11
Classifier: Programming Language :: Python :: 3.12
Requires-Dist: PyNomaly (>=0.3.3)
Requires-Dist: beautifulsoup4 (>=4.11.1)
Requires-Dist: category-encoders (>=2.3.0)
Requires-Dist: ipykernel (>=5.3.0)
Requires-Dist: ipywidgets (>=8)
Requires-Dist: jinja2 (>=3.0.1)
Requires-Dist: jsonpickle (>=2)
Requires-Dist: matplotlib (>=3.0.1)
Requires-Dist: pandas (>=1.1.5,<2.3.0)
Requires-Dist: plotly (>=5.0.1)
Requires-Dist: scikit-learn (<1.6.0)
Requires-Dist: setuptools
Requires-Dist: tqdm (>=4.62.3)
